package androidx.appcompat.widget;

import android.os.AsyncTask;

final class ActivityChooserModel$PersistHistoryAsyncTask
  extends AsyncTask
{
  public ActivityChooserModel$PersistHistoryAsyncTask(ActivityChooserModel paramActivityChooserModel) {}
  
  /* Error */
  public java.lang.Void OooO00o(java.lang.Object... paramVarArgs)
  {
    // Byte code:
    //   0: ldc 14
    //   2: astore_2
    //   3: ldc 16
    //   5: astore_3
    //   6: ldc 18
    //   8: astore 4
    //   10: aload_1
    //   11: iconst_0
    //   12: aaload
    //   13: checkcast 20	java/util/List
    //   16: astore 5
    //   18: iconst_1
    //   19: istore 6
    //   21: aload_1
    //   22: iload 6
    //   24: aaload
    //   25: checkcast 23	java/lang/String
    //   28: astore_1
    //   29: aload_0
    //   30: getfield 8	androidx/appcompat/widget/ActivityChooserModel$PersistHistoryAsyncTask:OooO00o	Landroidx/appcompat/widget/ActivityChooserModel;
    //   33: astore 7
    //   35: aload 7
    //   37: getfield 29	androidx/appcompat/widget/ActivityChooserModel:OooO0Oo	Landroid/content/Context;
    //   40: astore 7
    //   42: aload 7
    //   44: aload_1
    //   45: iconst_0
    //   46: invokevirtual 35	android/content/Context:openFileOutput	(Ljava/lang/String;I)Ljava/io/FileOutputStream;
    //   49: astore_1
    //   50: invokestatic 41	android/util/Xml:newSerializer	()Lorg/xmlpull/v1/XmlSerializer;
    //   53: astore 7
    //   55: aload 7
    //   57: aload_1
    //   58: aconst_null
    //   59: invokeinterface 47 3 0
    //   64: ldc 49
    //   66: astore 8
    //   68: getstatic 55	java/lang/Boolean:TRUE	Ljava/lang/Boolean;
    //   71: astore 9
    //   73: aload 7
    //   75: aload 8
    //   77: aload 9
    //   79: invokeinterface 59 3 0
    //   84: aload 7
    //   86: aconst_null
    //   87: aload_3
    //   88: invokeinterface 63 3 0
    //   93: pop
    //   94: aload 5
    //   96: invokeinterface 67 1 0
    //   101: istore 10
    //   103: iconst_0
    //   104: istore 11
    //   106: aconst_null
    //   107: astore 9
    //   109: iload 11
    //   111: iload 10
    //   113: if_icmpge +142 -> 255
    //   116: aload 5
    //   118: iconst_0
    //   119: invokeinterface 71 2 0
    //   124: astore 12
    //   126: aload 12
    //   128: checkcast 73	androidx/appcompat/widget/ActivityChooserModel$HistoricalRecord
    //   131: astore 12
    //   133: aload 7
    //   135: aconst_null
    //   136: aload_2
    //   137: invokeinterface 63 3 0
    //   142: pop
    //   143: ldc 75
    //   145: astore 13
    //   147: aload 12
    //   149: getfield 78	androidx/appcompat/widget/ActivityChooserModel$HistoricalRecord:OooO00o	Landroid/content/ComponentName;
    //   152: astore 14
    //   154: aload 14
    //   156: invokevirtual 84	android/content/ComponentName:flattenToString	()Ljava/lang/String;
    //   159: astore 14
    //   161: aload 7
    //   163: aconst_null
    //   164: aload 13
    //   166: aload 14
    //   168: invokeinterface 88 4 0
    //   173: pop
    //   174: ldc 90
    //   176: astore 13
    //   178: aload 12
    //   180: getfield 94	androidx/appcompat/widget/ActivityChooserModel$HistoricalRecord:OooO0O0	J
    //   183: lstore 15
    //   185: lload 15
    //   187: invokestatic 98	java/lang/String:valueOf	(J)Ljava/lang/String;
    //   190: astore 14
    //   192: aload 7
    //   194: aconst_null
    //   195: aload 13
    //   197: aload 14
    //   199: invokeinterface 88 4 0
    //   204: pop
    //   205: ldc 100
    //   207: astore 13
    //   209: aload 12
    //   211: getfield 104	androidx/appcompat/widget/ActivityChooserModel$HistoricalRecord:OooO0OO	F
    //   214: fstore 17
    //   216: fload 17
    //   218: invokestatic 107	java/lang/String:valueOf	(F)Ljava/lang/String;
    //   221: astore 12
    //   223: aload 7
    //   225: aconst_null
    //   226: aload 13
    //   228: aload 12
    //   230: invokeinterface 88 4 0
    //   235: pop
    //   236: aload 7
    //   238: aconst_null
    //   239: aload_2
    //   240: invokeinterface 110 3 0
    //   245: pop
    //   246: iload 11
    //   248: iconst_1
    //   249: iadd
    //   250: istore 11
    //   252: goto -143 -> 109
    //   255: aload 7
    //   257: aconst_null
    //   258: aload_3
    //   259: invokeinterface 110 3 0
    //   264: pop
    //   265: aload 7
    //   267: invokeinterface 113 1 0
    //   272: aload_0
    //   273: getfield 8	androidx/appcompat/widget/ActivityChooserModel$PersistHistoryAsyncTask:OooO00o	Landroidx/appcompat/widget/ActivityChooserModel;
    //   276: astore_2
    //   277: aload_2
    //   278: iload 6
    //   280: putfield 117	androidx/appcompat/widget/ActivityChooserModel:OooO	Z
    //   283: aload_1
    //   284: ifnull +177 -> 461
    //   287: aload_1
    //   288: invokevirtual 122	java/io/FileOutputStream:close	()V
    //   291: goto +170 -> 461
    //   294: astore_2
    //   295: goto +168 -> 463
    //   298: pop
    //   299: getstatic 126	androidx/appcompat/widget/ActivityChooserModel:OooOOO	Ljava/lang/Object;
    //   302: astore_2
    //   303: new 128	java/lang/StringBuilder
    //   306: astore_2
    //   307: aload_2
    //   308: invokespecial 129	java/lang/StringBuilder:<init>	()V
    //   311: aload_2
    //   312: aload 4
    //   314: invokevirtual 133	java/lang/StringBuilder:append	(Ljava/lang/String;)Ljava/lang/StringBuilder;
    //   317: pop
    //   318: aload_0
    //   319: getfield 8	androidx/appcompat/widget/ActivityChooserModel$PersistHistoryAsyncTask:OooO00o	Landroidx/appcompat/widget/ActivityChooserModel;
    //   322: astore_3
    //   323: aload_3
    //   324: getfield 137	androidx/appcompat/widget/ActivityChooserModel:OooO0o0	Ljava/lang/String;
    //   327: astore_3
    //   328: aload_2
    //   329: aload_3
    //   330: invokevirtual 133	java/lang/StringBuilder:append	(Ljava/lang/String;)Ljava/lang/StringBuilder;
    //   333: pop
    //   334: aload_0
    //   335: getfield 8	androidx/appcompat/widget/ActivityChooserModel$PersistHistoryAsyncTask:OooO00o	Landroidx/appcompat/widget/ActivityChooserModel;
    //   338: astore_2
    //   339: aload_2
    //   340: iload 6
    //   342: putfield 117	androidx/appcompat/widget/ActivityChooserModel:OooO	Z
    //   345: aload_1
    //   346: ifnull +115 -> 461
    //   349: goto -62 -> 287
    //   352: pop
    //   353: getstatic 126	androidx/appcompat/widget/ActivityChooserModel:OooOOO	Ljava/lang/Object;
    //   356: astore_2
    //   357: new 128	java/lang/StringBuilder
    //   360: astore_2
    //   361: aload_2
    //   362: invokespecial 129	java/lang/StringBuilder:<init>	()V
    //   365: aload_2
    //   366: aload 4
    //   368: invokevirtual 133	java/lang/StringBuilder:append	(Ljava/lang/String;)Ljava/lang/StringBuilder;
    //   371: pop
    //   372: aload_0
    //   373: getfield 8	androidx/appcompat/widget/ActivityChooserModel$PersistHistoryAsyncTask:OooO00o	Landroidx/appcompat/widget/ActivityChooserModel;
    //   376: astore_3
    //   377: aload_3
    //   378: getfield 137	androidx/appcompat/widget/ActivityChooserModel:OooO0o0	Ljava/lang/String;
    //   381: astore_3
    //   382: aload_2
    //   383: aload_3
    //   384: invokevirtual 133	java/lang/StringBuilder:append	(Ljava/lang/String;)Ljava/lang/StringBuilder;
    //   387: pop
    //   388: aload_0
    //   389: getfield 8	androidx/appcompat/widget/ActivityChooserModel$PersistHistoryAsyncTask:OooO00o	Landroidx/appcompat/widget/ActivityChooserModel;
    //   392: astore_2
    //   393: aload_2
    //   394: iload 6
    //   396: putfield 117	androidx/appcompat/widget/ActivityChooserModel:OooO	Z
    //   399: aload_1
    //   400: ifnull +61 -> 461
    //   403: goto -116 -> 287
    //   406: pop
    //   407: getstatic 126	androidx/appcompat/widget/ActivityChooserModel:OooOOO	Ljava/lang/Object;
    //   410: astore_2
    //   411: new 128	java/lang/StringBuilder
    //   414: astore_2
    //   415: aload_2
    //   416: invokespecial 129	java/lang/StringBuilder:<init>	()V
    //   419: aload_2
    //   420: aload 4
    //   422: invokevirtual 133	java/lang/StringBuilder:append	(Ljava/lang/String;)Ljava/lang/StringBuilder;
    //   425: pop
    //   426: aload_0
    //   427: getfield 8	androidx/appcompat/widget/ActivityChooserModel$PersistHistoryAsyncTask:OooO00o	Landroidx/appcompat/widget/ActivityChooserModel;
    //   430: astore_3
    //   431: aload_3
    //   432: getfield 137	androidx/appcompat/widget/ActivityChooserModel:OooO0o0	Ljava/lang/String;
    //   435: astore_3
    //   436: aload_2
    //   437: aload_3
    //   438: invokevirtual 133	java/lang/StringBuilder:append	(Ljava/lang/String;)Ljava/lang/StringBuilder;
    //   441: pop
    //   442: aload_0
    //   443: getfield 8	androidx/appcompat/widget/ActivityChooserModel$PersistHistoryAsyncTask:OooO00o	Landroidx/appcompat/widget/ActivityChooserModel;
    //   446: astore_2
    //   447: aload_2
    //   448: iload 6
    //   450: putfield 117	androidx/appcompat/widget/ActivityChooserModel:OooO	Z
    //   453: aload_1
    //   454: ifnull +7 -> 461
    //   457: goto -170 -> 287
    //   460: pop
    //   461: aconst_null
    //   462: areturn
    //   463: aload_0
    //   464: getfield 8	androidx/appcompat/widget/ActivityChooserModel$PersistHistoryAsyncTask:OooO00o	Landroidx/appcompat/widget/ActivityChooserModel;
    //   467: astore_3
    //   468: aload_3
    //   469: iload 6
    //   471: putfield 117	androidx/appcompat/widget/ActivityChooserModel:OooO	Z
    //   474: aload_1
    //   475: ifnull +7 -> 482
    //   478: aload_1
    //   479: invokevirtual 122	java/io/FileOutputStream:close	()V
    //   482: aload_2
    //   483: athrow
    //   484: pop
    //   485: getstatic 126	androidx/appcompat/widget/ActivityChooserModel:OooOOO	Ljava/lang/Object;
    //   488: astore_2
    //   489: new 128	java/lang/StringBuilder
    //   492: astore_2
    //   493: aload_2
    //   494: invokespecial 129	java/lang/StringBuilder:<init>	()V
    //   497: aload_2
    //   498: aload 4
    //   500: invokevirtual 133	java/lang/StringBuilder:append	(Ljava/lang/String;)Ljava/lang/StringBuilder;
    //   503: pop
    //   504: aload_2
    //   505: aload_1
    //   506: invokevirtual 133	java/lang/StringBuilder:append	(Ljava/lang/String;)Ljava/lang/StringBuilder;
    //   509: pop
    //   510: aconst_null
    //   511: areturn
    //   512: pop
    //   513: goto -31 -> 482
    // Local variable table:
    //   start	length	slot	name	signature
    //   0	516	0	this	PersistHistoryAsyncTask
    //   0	516	1	paramVarArgs	java.lang.Object[]
    //   2	276	2	localObject1	java.lang.Object
    //   294	1	2	localObject2	java.lang.Object
    //   302	203	2	localObject3	java.lang.Object
    //   5	464	3	localObject4	java.lang.Object
    //   8	491	4	str1	java.lang.String
    //   16	101	5	localList	java.util.List
    //   19	451	6	bool	boolean
    //   33	233	7	localObject5	java.lang.Object
    //   66	10	8	str2	java.lang.String
    //   71	37	9	localBoolean	java.lang.Boolean
    //   101	13	10	i	int
    //   104	147	11	j	int
    //   124	105	12	localObject6	java.lang.Object
    //   145	82	13	str3	java.lang.String
    //   152	46	14	localObject7	java.lang.Object
    //   183	3	15	l	long
    //   214	3	17	f	float
    //   298	1	19	localIOException1	java.io.IOException
    //   352	1	20	localIllegalStateException	java.lang.IllegalStateException
    //   406	1	21	localIllegalArgumentException	java.lang.IllegalArgumentException
    //   460	1	22	localIOException2	java.io.IOException
    //   484	1	23	localFileNotFoundException	java.io.FileNotFoundException
    //   512	1	24	localIOException3	java.io.IOException
    // Exception table:
    //   from	to	target	type
    //   58	64	294	finally
    //   68	71	294	finally
    //   77	84	294	finally
    //   87	94	294	finally
    //   94	101	294	finally
    //   118	124	294	finally
    //   126	131	294	finally
    //   136	143	294	finally
    //   147	152	294	finally
    //   154	159	294	finally
    //   166	174	294	finally
    //   178	183	294	finally
    //   185	190	294	finally
    //   197	205	294	finally
    //   209	214	294	finally
    //   216	221	294	finally
    //   228	236	294	finally
    //   239	246	294	finally
    //   258	265	294	finally
    //   265	272	294	finally
    //   299	302	294	finally
    //   303	306	294	finally
    //   307	311	294	finally
    //   312	318	294	finally
    //   318	322	294	finally
    //   323	327	294	finally
    //   329	334	294	finally
    //   353	356	294	finally
    //   357	360	294	finally
    //   361	365	294	finally
    //   366	372	294	finally
    //   372	376	294	finally
    //   377	381	294	finally
    //   383	388	294	finally
    //   407	410	294	finally
    //   411	414	294	finally
    //   415	419	294	finally
    //   420	426	294	finally
    //   426	430	294	finally
    //   431	435	294	finally
    //   437	442	294	finally
    //   58	64	298	java/io/IOException
    //   68	71	298	java/io/IOException
    //   77	84	298	java/io/IOException
    //   87	94	298	java/io/IOException
    //   94	101	298	java/io/IOException
    //   118	124	298	java/io/IOException
    //   126	131	298	java/io/IOException
    //   136	143	298	java/io/IOException
    //   147	152	298	java/io/IOException
    //   154	159	298	java/io/IOException
    //   166	174	298	java/io/IOException
    //   178	183	298	java/io/IOException
    //   185	190	298	java/io/IOException
    //   197	205	298	java/io/IOException
    //   209	214	298	java/io/IOException
    //   216	221	298	java/io/IOException
    //   228	236	298	java/io/IOException
    //   239	246	298	java/io/IOException
    //   258	265	298	java/io/IOException
    //   265	272	298	java/io/IOException
    //   58	64	352	java/lang/IllegalStateException
    //   68	71	352	java/lang/IllegalStateException
    //   77	84	352	java/lang/IllegalStateException
    //   87	94	352	java/lang/IllegalStateException
    //   94	101	352	java/lang/IllegalStateException
    //   118	124	352	java/lang/IllegalStateException
    //   126	131	352	java/lang/IllegalStateException
    //   136	143	352	java/lang/IllegalStateException
    //   147	152	352	java/lang/IllegalStateException
    //   154	159	352	java/lang/IllegalStateException
    //   166	174	352	java/lang/IllegalStateException
    //   178	183	352	java/lang/IllegalStateException
    //   185	190	352	java/lang/IllegalStateException
    //   197	205	352	java/lang/IllegalStateException
    //   209	214	352	java/lang/IllegalStateException
    //   216	221	352	java/lang/IllegalStateException
    //   228	236	352	java/lang/IllegalStateException
    //   239	246	352	java/lang/IllegalStateException
    //   258	265	352	java/lang/IllegalStateException
    //   265	272	352	java/lang/IllegalStateException
    //   58	64	406	java/lang/IllegalArgumentException
    //   68	71	406	java/lang/IllegalArgumentException
    //   77	84	406	java/lang/IllegalArgumentException
    //   87	94	406	java/lang/IllegalArgumentException
    //   94	101	406	java/lang/IllegalArgumentException
    //   118	124	406	java/lang/IllegalArgumentException
    //   126	131	406	java/lang/IllegalArgumentException
    //   136	143	406	java/lang/IllegalArgumentException
    //   147	152	406	java/lang/IllegalArgumentException
    //   154	159	406	java/lang/IllegalArgumentException
    //   166	174	406	java/lang/IllegalArgumentException
    //   178	183	406	java/lang/IllegalArgumentException
    //   185	190	406	java/lang/IllegalArgumentException
    //   197	205	406	java/lang/IllegalArgumentException
    //   209	214	406	java/lang/IllegalArgumentException
    //   216	221	406	java/lang/IllegalArgumentException
    //   228	236	406	java/lang/IllegalArgumentException
    //   239	246	406	java/lang/IllegalArgumentException
    //   258	265	406	java/lang/IllegalArgumentException
    //   265	272	406	java/lang/IllegalArgumentException
    //   287	291	460	java/io/IOException
    //   29	33	484	java/io/FileNotFoundException
    //   35	40	484	java/io/FileNotFoundException
    //   45	49	484	java/io/FileNotFoundException
    //   478	482	512	java/io/IOException
  }
}


/* Location:           G:\apknx\enjarify-master\com.cunba.lantu.otan-enjarify.jar
 * Qualified Name:     androidx.appcompat.widget.ActivityChooserModel.PersistHistoryAsyncTask
 * JD-Core Version:    0.7.0.1
 */