package com.qinggan.media;

class ImageCache$2
  implements Runnable
{
  /* Error */
  public void run()
  {
    // Byte code:
    //   0: aload_0
    //   1: getfield 14	com/qinggan/media/ImageCache$2:o00OoOoo	Lcom/qinggan/media/ImageCache;
    //   4: invokestatic 20	com/qinggan/media/ImageCache:OooO00o	(Lcom/qinggan/media/ImageCache;)Ljava/lang/Object;
    //   7: astore_1
    //   8: aload_1
    //   9: monitorenter
    //   10: aload_0
    //   11: getfield 14	com/qinggan/media/ImageCache$2:o00OoOoo	Lcom/qinggan/media/ImageCache;
    //   14: astore_2
    //   15: aload_2
    //   16: invokestatic 24	com/qinggan/media/ImageCache:OooO0O0	(Lcom/qinggan/media/ImageCache;)Lcom/qinggan/media/DiskLruCache;
    //   19: astore_2
    //   20: aload_2
    //   21: ifnull +307 -> 328
    //   24: aload_0
    //   25: getfield 26	com/qinggan/media/ImageCache$2:o00Ooo0	Ljava/lang/String;
    //   28: astore_2
    //   29: aload_2
    //   30: invokestatic 30	com/qinggan/media/ImageCache:OooO0oO	(Ljava/lang/String;)Ljava/lang/String;
    //   33: astore_2
    //   34: new 32	java/lang/StringBuilder
    //   37: astore_3
    //   38: aload_3
    //   39: invokespecial 36	java/lang/StringBuilder:<init>	()V
    //   42: ldc 38
    //   44: astore 4
    //   46: aload 4
    //   48: invokestatic 43	m54207b69:F54207b69_11	(Ljava/lang/String;)Ljava/lang/String;
    //   51: astore 4
    //   53: aload_3
    //   54: aload 4
    //   56: invokevirtual 47	java/lang/StringBuilder:append	(Ljava/lang/String;)Ljava/lang/StringBuilder;
    //   59: pop
    //   60: aload_3
    //   61: aload_2
    //   62: invokevirtual 47	java/lang/StringBuilder:append	(Ljava/lang/String;)Ljava/lang/StringBuilder;
    //   65: pop
    //   66: aconst_null
    //   67: astore_3
    //   68: aload_0
    //   69: getfield 14	com/qinggan/media/ImageCache$2:o00OoOoo	Lcom/qinggan/media/ImageCache;
    //   72: astore 4
    //   74: aload 4
    //   76: invokestatic 24	com/qinggan/media/ImageCache:OooO0O0	(Lcom/qinggan/media/ImageCache;)Lcom/qinggan/media/DiskLruCache;
    //   79: astore 4
    //   81: aload 4
    //   83: aload_2
    //   84: invokevirtual 53	com/qinggan/media/DiskLruCache:Oooo000	(Ljava/lang/String;)Lcom/qinggan/media/DiskLruCache$Snapshot;
    //   87: astore 4
    //   89: aconst_null
    //   90: astore 5
    //   92: aload 4
    //   94: ifnonnull +110 -> 204
    //   97: aload_0
    //   98: getfield 14	com/qinggan/media/ImageCache$2:o00OoOoo	Lcom/qinggan/media/ImageCache;
    //   101: astore 4
    //   103: aload 4
    //   105: invokestatic 24	com/qinggan/media/ImageCache:OooO0O0	(Lcom/qinggan/media/ImageCache;)Lcom/qinggan/media/DiskLruCache;
    //   108: astore 4
    //   110: aload 4
    //   112: aload_2
    //   113: invokevirtual 57	com/qinggan/media/DiskLruCache:OooOooO	(Ljava/lang/String;)Lcom/qinggan/media/DiskLruCache$Editor;
    //   116: astore_2
    //   117: aload_2
    //   118: ifnull +97 -> 215
    //   121: aload_2
    //   122: iconst_0
    //   123: invokevirtual 63	com/qinggan/media/DiskLruCache$Editor:OooO0o	(I)Ljava/io/OutputStream;
    //   126: astore_3
    //   127: aload_0
    //   128: getfield 65	com/qinggan/media/ImageCache$2:o00Ooo00	Landroid/graphics/Bitmap;
    //   131: astore 4
    //   133: aload_0
    //   134: getfield 14	com/qinggan/media/ImageCache$2:o00OoOoo	Lcom/qinggan/media/ImageCache;
    //   137: astore 5
    //   139: aload 5
    //   141: invokestatic 69	com/qinggan/media/ImageCache:OooO0OO	(Lcom/qinggan/media/ImageCache;)Lcom/qinggan/media/ImageCache$ImageCacheParams;
    //   144: astore 5
    //   146: aload 5
    //   148: getfield 74	com/qinggan/media/ImageCache$ImageCacheParams:OooO00o	Landroid/graphics/Bitmap$CompressFormat;
    //   151: astore 5
    //   153: aload_0
    //   154: getfield 14	com/qinggan/media/ImageCache$2:o00OoOoo	Lcom/qinggan/media/ImageCache;
    //   157: astore 6
    //   159: aload 6
    //   161: invokestatic 69	com/qinggan/media/ImageCache:OooO0OO	(Lcom/qinggan/media/ImageCache;)Lcom/qinggan/media/ImageCache$ImageCacheParams;
    //   164: astore 6
    //   166: aload 6
    //   168: getfield 77	com/qinggan/media/ImageCache$ImageCacheParams:OooO0O0	I
    //   171: istore 7
    //   173: aload 4
    //   175: aload 5
    //   177: iload 7
    //   179: aload_3
    //   180: invokevirtual 83	android/graphics/Bitmap:compress	(Landroid/graphics/Bitmap$CompressFormat;ILjava/io/OutputStream;)Z
    //   183: pop
    //   184: aload_2
    //   185: invokevirtual 86	com/qinggan/media/DiskLruCache$Editor:OooO0Oo	()V
    //   188: aload_3
    //   189: invokevirtual 91	java/io/OutputStream:close	()V
    //   192: aload_0
    //   193: getfield 14	com/qinggan/media/ImageCache$2:o00OoOoo	Lcom/qinggan/media/ImageCache;
    //   196: astore_2
    //   197: aload_2
    //   198: invokevirtual 94	com/qinggan/media/ImageCache:OooO0o0	()V
    //   201: goto +14 -> 215
    //   204: aload 4
    //   206: iconst_0
    //   207: invokevirtual 100	com/qinggan/media/DiskLruCache$Snapshot:getInputStream	(I)Ljava/io/InputStream;
    //   210: astore_2
    //   211: aload_2
    //   212: invokevirtual 103	java/io/InputStream:close	()V
    //   215: aload_3
    //   216: ifnull +112 -> 328
    //   219: aload_3
    //   220: invokevirtual 91	java/io/OutputStream:close	()V
    //   223: goto +105 -> 328
    //   226: astore_2
    //   227: goto +91 -> 318
    //   230: astore_2
    //   231: new 32	java/lang/StringBuilder
    //   234: astore 4
    //   236: aload 4
    //   238: invokespecial 36	java/lang/StringBuilder:<init>	()V
    //   241: ldc 105
    //   243: astore 5
    //   245: aload 5
    //   247: invokestatic 43	m54207b69:F54207b69_11	(Ljava/lang/String;)Ljava/lang/String;
    //   250: astore 5
    //   252: aload 4
    //   254: aload 5
    //   256: invokevirtual 47	java/lang/StringBuilder:append	(Ljava/lang/String;)Ljava/lang/StringBuilder;
    //   259: pop
    //   260: aload 4
    //   262: aload_2
    //   263: invokevirtual 108	java/lang/StringBuilder:append	(Ljava/lang/Object;)Ljava/lang/StringBuilder;
    //   266: pop
    //   267: aload_3
    //   268: ifnull +60 -> 328
    //   271: goto -52 -> 219
    //   274: astore_2
    //   275: new 32	java/lang/StringBuilder
    //   278: astore 4
    //   280: aload 4
    //   282: invokespecial 36	java/lang/StringBuilder:<init>	()V
    //   285: ldc 105
    //   287: astore 5
    //   289: aload 5
    //   291: invokestatic 43	m54207b69:F54207b69_11	(Ljava/lang/String;)Ljava/lang/String;
    //   294: astore 5
    //   296: aload 4
    //   298: aload 5
    //   300: invokevirtual 47	java/lang/StringBuilder:append	(Ljava/lang/String;)Ljava/lang/StringBuilder;
    //   303: pop
    //   304: aload 4
    //   306: aload_2
    //   307: invokevirtual 108	java/lang/StringBuilder:append	(Ljava/lang/Object;)Ljava/lang/StringBuilder;
    //   310: pop
    //   311: aload_3
    //   312: ifnull +16 -> 328
    //   315: goto -96 -> 219
    //   318: aload_3
    //   319: ifnull +7 -> 326
    //   322: aload_3
    //   323: invokevirtual 91	java/io/OutputStream:close	()V
    //   326: aload_2
    //   327: athrow
    //   328: aload_1
    //   329: monitorexit
    //   330: return
    //   331: astore_2
    //   332: aload_1
    //   333: monitorexit
    //   334: aload_2
    //   335: athrow
    //   336: pop
    //   337: goto -11 -> 326
    //   340: pop
    //   341: goto -13 -> 328
    // Local variable table:
    //   start	length	slot	name	signature
    //   0	344	0	this	2
    //   7	326	1	localObject1	Object
    //   14	198	2	localObject2	Object
    //   226	1	2	localObject3	Object
    //   230	33	2	localException	java.lang.Exception
    //   274	53	2	localIOException1	java.io.IOException
    //   331	4	2	localObject4	Object
    //   37	286	3	localObject5	Object
    //   44	261	4	localObject6	Object
    //   90	209	5	localObject7	Object
    //   157	10	6	localObject8	Object
    //   171	7	7	i	int
    //   336	1	12	localIOException2	java.io.IOException
    //   340	1	13	localIOException3	java.io.IOException
    // Exception table:
    //   from	to	target	type
    //   68	72	226	finally
    //   74	79	226	finally
    //   83	87	226	finally
    //   97	101	226	finally
    //   103	108	226	finally
    //   112	116	226	finally
    //   122	126	226	finally
    //   127	131	226	finally
    //   133	137	226	finally
    //   139	144	226	finally
    //   146	151	226	finally
    //   153	157	226	finally
    //   159	164	226	finally
    //   166	171	226	finally
    //   179	184	226	finally
    //   184	188	226	finally
    //   188	192	226	finally
    //   192	196	226	finally
    //   197	201	226	finally
    //   206	210	226	finally
    //   211	215	226	finally
    //   231	234	226	finally
    //   236	241	226	finally
    //   245	250	226	finally
    //   254	260	226	finally
    //   262	267	226	finally
    //   275	278	226	finally
    //   280	285	226	finally
    //   289	294	226	finally
    //   298	304	226	finally
    //   306	311	226	finally
    //   68	72	230	java/lang/Exception
    //   74	79	230	java/lang/Exception
    //   83	87	230	java/lang/Exception
    //   97	101	230	java/lang/Exception
    //   103	108	230	java/lang/Exception
    //   112	116	230	java/lang/Exception
    //   122	126	230	java/lang/Exception
    //   127	131	230	java/lang/Exception
    //   133	137	230	java/lang/Exception
    //   139	144	230	java/lang/Exception
    //   146	151	230	java/lang/Exception
    //   153	157	230	java/lang/Exception
    //   159	164	230	java/lang/Exception
    //   166	171	230	java/lang/Exception
    //   179	184	230	java/lang/Exception
    //   184	188	230	java/lang/Exception
    //   188	192	230	java/lang/Exception
    //   192	196	230	java/lang/Exception
    //   197	201	230	java/lang/Exception
    //   206	210	230	java/lang/Exception
    //   211	215	230	java/lang/Exception
    //   68	72	274	java/io/IOException
    //   74	79	274	java/io/IOException
    //   83	87	274	java/io/IOException
    //   97	101	274	java/io/IOException
    //   103	108	274	java/io/IOException
    //   112	116	274	java/io/IOException
    //   122	126	274	java/io/IOException
    //   127	131	274	java/io/IOException
    //   133	137	274	java/io/IOException
    //   139	144	274	java/io/IOException
    //   146	151	274	java/io/IOException
    //   153	157	274	java/io/IOException
    //   159	164	274	java/io/IOException
    //   166	171	274	java/io/IOException
    //   179	184	274	java/io/IOException
    //   184	188	274	java/io/IOException
    //   188	192	274	java/io/IOException
    //   192	196	274	java/io/IOException
    //   197	201	274	java/io/IOException
    //   206	210	274	java/io/IOException
    //   211	215	274	java/io/IOException
    //   10	14	331	finally
    //   15	19	331	finally
    //   24	28	331	finally
    //   29	33	331	finally
    //   34	37	331	finally
    //   38	42	331	finally
    //   46	51	331	finally
    //   54	60	331	finally
    //   61	66	331	finally
    //   219	223	331	finally
    //   322	326	331	finally
    //   326	328	331	finally
    //   328	330	331	finally
    //   332	334	331	finally
    //   322	326	336	java/io/IOException
    //   219	223	340	java/io/IOException
  }
}


/* Location:           G:\apknx\enjarify-master\com.cunba.lantu.otan-enjarify.jar
 * Qualified Name:     com.qinggan.media.ImageCache.2
 * JD-Core Version:    0.7.0.1
 */